{
  "updated": "2026-07-09T00:07:20Z",
  "location": {
    "name": "Observatory Station"
  },
  "surface": {
    "temp_c": 29.3,
    "humidity_pct": 47,
    "wind_kmh": 9.2,
    "wind_dir": 249,
    "pressure_hpa": 1015.1,
    "cloud_pct": 6,
    "feels_c": 30.3,
    "precip_mm": 0.0,
    "weather_code": 0,
    "today_max": 31.8,
    "today_min": 21.7,
    "sunrise": "2026-07-08T06:24",
    "sunset": "2026-07-08T20:52",
    "precip_sum_mm": 0.0,
    "wind_hourly": [
      {
        "h": "20:00",
        "w": 9.2,
        "g": 15.8
      },
      {
        "h": "21:00",
        "w": 4.0,
        "g": 14.8
      },
      {
        "h": "22:00",
        "w": 3.1,
        "g": 12.2
      },
      {
        "h": "23:00",
        "w": 3.1,
        "g": 13.0
      }
    ]
  },
  "air_quality": {
    "us_aqi": 66,
    "pm25": 5.8,
    "pm10": 6.2,
    "ozone": 101.0,
    "no2": 2.8
  },
  "ionosphere": {
    "tec": 18.402664530902072,
    "hmf2_km": 296.1616150892565,
    "anomaly": -9.073167753995282
  },
  "magnetosphere": {
    "kp_now": 2.33,
    "kp_24h_min": 1.7,
    "kp_24h_max": 3.3,
    "kp_24h_mean": 2.7,
    "kp_time": "2026-07-08T21:00:00",
    "kp_1m": 0.0,
    "dst_nt": -27.7,
    "dst_flag": "quiet"
  },
  "solar_wind": {
    "bt_nt": 7.55,
    "bz_nt": -6.22,
    "bz_gsm_nt": -6.36,
    "time": "2026-07-08T00:06:00",
    "bz_flag": "strongly southward",
    "speed_kms": 400.33,
    "density": 1.15,
    "temp_k": 60894.0
  },
  "sun": {
    "xray_flux": 5.777e-07,
    "xray_peak": 1.55569e-05,
    "xray_class": "B",
    "xray_peak_class": "M",
    "latest_flare": "B6.9\u2192M1.5",
    "flare_time": "2026-07-09T00:03:00Z",
    "proton_flux_pfu": 0.2,
    "sep_warning": false,
    "f107": 142.0,
    "active_regions": 0,
    "regions": []
  },
  "kp_forecast": [
    {
      "date": "07-10",
      "bins": [
        3.67,
        2.67,
        2.67,
        2.67,
        2.67,
        2.67,
        3.67,
        2.67
      ],
      "max": 3.67
    },
    {
      "date": "07-11",
      "bins": [
        3.67,
        2.0,
        2.0,
        2.67,
        2.67,
        2.67,
        2.67,
        3.0
      ],
      "max": 3.67
    },
    {
      "date": "07-12",
      "bins": [
        2.33
      ],
      "max": 2.33
    }
  ],
  "neo": {
    "count": 4,
    "objects": [
      {
        "name": "(2019 AM12)",
        "miss_ld": 28.1,
        "diameter_m": 49.4,
        "hazardous": false
      },
      {
        "name": "(2017 RO17)",
        "miss_ld": 130.7,
        "diameter_m": 35.8,
        "hazardous": false
      },
      {
        "name": "(2017 TH2)",
        "miss_ld": 132.1,
        "diameter_m": 10.3,
        "hazardous": false
      },
      {
        "name": "(2013 BU2)",
        "miss_ld": 139.7,
        "diameter_m": 171.4,
        "hazardous": false
      }
    ],
    "hazardous_count": 0,
    "closest_ld": 28.1
  },
  "iss_pass": null,
  "alerts": [],
  "birds": {
    "detections_24h": 300,
    "species_count": 14,
    "top_species": [
      {
        "name": "Carolina Wren",
        "count": 232
      },
      {
        "name": "American Goldfinch",
        "count": 39
      },
      {
        "name": "Northern Cardinal",
        "count": 9
      },
      {
        "name": "Red-shouldered Hawk",
        "count": 4
      },
      {
        "name": "Louisiana Waterthrush",
        "count": 4
      },
      {
        "name": "Eastern Bluebird",
        "count": 2
      },
      {
        "name": "Belted Kingfisher",
        "count": 2
      },
      {
        "name": "Yellow-throated Warbler",
        "count": 2
      }
    ],
    "recent": [
      {
        "species": "Yellow-throated Warbler",
        "confidence": 87.8,
        "time": "18:47:22"
      },
      {
        "species": "Downy Woodpecker",
        "confidence": 94.7,
        "time": "19:21:46"
      },
      {
        "species": "American Goldfinch",
        "confidence": 73.6,
        "time": "19:47:10"
      },
      {
        "species": "Northern Cardinal",
        "confidence": 75.4,
        "time": "19:50:55"
      },
      {
        "species": "American Goldfinch",
        "confidence": 71.2,
        "time": "19:58:10"
      }
    ]
  },
  "imagery": {
    "epic": "https://epic.gsfc.nasa.gov/archive/natural/2026/07/06/png/epic_1b_20260706234948.png",
    "sdo_aia171": "https://api.helioviewer.org/v2/downloadImage/?id=189752108&width=1024"
  }
}